xchrome.py
xchrome-1.0.0.dist-info/METADATA
xchrome-1.0.0.dist-info/WHEEL
xchrome-1.0.0.dist-info/entry_points.txt
xchrome-1.0.0.dist-info/top_level.txt
xchrome-1.0.0.dist-info/RECORD
